codeflash_benchmark/__init__.py
codeflash_benchmark/plugin.py
codeflash_benchmark-0.2.0.dist-info/METADATA
codeflash_benchmark-0.2.0.dist-info/WHEEL
codeflash_benchmark-0.2.0.dist-info/entry_points.txt
codeflash_benchmark-0.2.0.dist-info/top_level.txt
codeflash_benchmark-0.2.0.dist-info/RECORD
